atk_dinesh_project/__init__.py
atk_dinesh_project-0.1.0.dist-info/METADATA
atk_dinesh_project-0.1.0.dist-info/WHEEL
atk_dinesh_project-0.1.0.dist-info/entry_points.txt
atk_dinesh_project-0.1.0.dist-info/RECORD
