Metadata-Version: 2.1
Name: atk-dinesh-project
Version: 0.1.0
Summary: a test file to print helloworld and use matplotlib
Author: dinesh-acog
Author-email: dinesh@aganitha.ai
Requires-Python: >=3.11,<4.0
Classifier: Programming Language :: Python :: 3
Classifier: Programming Language :: Python :: 3.11
Classifier: Programming Language :: Python :: 3.12
Requires-Dist: matplotlib (>=3.8.2,<4.0.0)
Requires-Dist: typer (>=0.9.0,<0.10.0)
